textmonger/__init__.py
textmonger/power.py
textmonger/power_words.csv
textmonger/project.py
textmonger/readability.py
textmonger-1.0.4.dist-info/licenses/LICENSE
textmonger-1.0.4.dist-info/METADATA
textmonger-1.0.4.dist-info/WHEEL
textmonger-1.0.4.dist-info/entry_points.txt
textmonger-1.0.4.dist-info/top_level.txt
textmonger-1.0.4.dist-info/RECORD
