Metadata-Version: 2.4
Name: textmonger
Version: 1.0.4
Summary: A text analysis tool with readability, power word analysis, and NER visualization.
Project-URL: Source, https://github.com/oceanthunder/textmonger
Classifier: Programming Language :: Python :: 3
Classifier: License :: OSI Approved :: The Unlicense (Unlicense)
Classifier: Operating System :: OS Independent
Requires-Python: >=3.6
License-File: LICENSE
Requires-Dist: spacy
Requires-Dist: pyfiglet
Requires-Dist: textstat
Requires-Dist: tabulate
Requires-Dist: textblob
Dynamic: classifier
Dynamic: description
Dynamic: description-content-type
Dynamic: license-file
Dynamic: project-url
Dynamic: requires-dist
Dynamic: requires-python
Dynamic: summary
